topicvelo/.DS_Store
topicvelo/__init__.py
topicvelo/dist_pl.py
topicvelo/embed_pl.py
topicvelo/inference_tools.py
topicvelo/tm_utils.py
topicvelo/transcription_simulation.py
topicvelo/transition_matrix.py
topicvelo/vel_eval_utils.py
topicvelo-0.0.2.dist-info/METADATA
topicvelo-0.0.2.dist-info/WHEEL
topicvelo-0.0.2.dist-info/licenses/LICENSE.txt
topicvelo-0.0.2.dist-info/RECORD
