Metadata-Version: 2.1
Name: topicvelo
Version: 0.0.2
Summary: TopicVelo: Dissection and Integration of Bursty Transcriptional Dynamics for Complex Systems
Project-URL: Homepage, https://github.com/chengfgao/TopicVelo
Project-URL: Bug Tracker, https://github.com/chengfgao/TopicVelo/issues
Author: Frank Gao
Maintainer-email: Frank Gao <frankgao19@uchicago.edu>
License: BSD 3-Clause License
License-File: LICENSE.txt
Keywords: RNA,single cell,stochastic,topic modeling,transcriptional bursting,transcriptomics,velocity
Classifier: Development Status :: 1 - Planning
Classifier: Intended Audience :: Science/Research
Classifier: License :: OSI Approved :: BSD License
Classifier: Natural Language :: English
Classifier: Programming Language :: Python :: 3
Classifier: Topic :: Scientific/Engineering :: Bio-Informatics
Classifier: Topic :: Scientific/Engineering :: Visualization
Requires-Python: >=3.7
Requires-Dist: anndata>=0.7.5
Requires-Dist: deeptime>=0.4.3
Requires-Dist: loompy>=2.0.12
Requires-Dist: matplotlib>=3.3.0
Requires-Dist: numba>=0.41.0
Requires-Dist: numpy>=1.17
Requires-Dist: pandas!=1.4.0,>=1.1.1
Requires-Dist: scanpy>=1.5
Requires-Dist: scikit-learn<1.2.0,>=0.21.2
Requires-Dist: scipy>=1.4.1
Requires-Dist: scvelo>=0.2.1
Requires-Dist: umap-learn>=0.3.10
